<?xml version="1.0" encoding="UTF-8"?>
<GenRun Id="impl_1" LaunchPart="xc7z010clg400-1" LaunchTime="1713309841">
  <File Type="PWROPT-DCP" Name="contBCD_VIO_pwropt.dcp"/>
  <File Type="ROUTE-PWR" Name="contBCD_VIO_power_routed.rpt"/>
  <File Type="PA-TCL" Name="contBCD_VIO.tcl"/>
  <File Type="ROUTE-PWR-SUM" Name="contBCD_VIO_power_summary_routed.pb"/>
  <File Type="REPORTS-TCL" Name="contBCD_VIO_reports.tcl"/>
  <File Type="BG-DRC" Name="contBCD_VIO.drc"/>
  <File Type="OPT-METHODOLOGY-DRC" Name="contBCD_VIO_methodology_drc_opted.rpt"/>
  <File Type="INIT-TIMING" Name="contBCD_VIO_timing_summary_init.rpt"/>
  <File Type="OPT-HWDEF" Name="contBCD_VIO.hwdef"/>
  <File Type="OPT-DCP" Name="contBCD_VIO_opt.dcp"/>
  <File Type="OPT-DRC" Name="contBCD_VIO_drc_opted.rpt"/>
  <File Type="OPT-TIMING" Name="contBCD_VIO_timing_summary_opted.rpt"/>
  <File Type="PWROPT-DRC" Name="contBCD_VIO_drc_pwropted.rpt"/>
  <File Type="PWROPT-TIMING" Name="contBCD_VIO_timing_summary_pwropted.rpt"/>
  <File Type="PLACE-DCP" Name="contBCD_VIO_placed.dcp"/>
  <File Type="PLACE-IO" Name="contBCD_VIO_io_placed.rpt"/>
  <File Type="PLACE-CLK" Name="contBCD_VIO_clock_utilization_placed.rpt"/>
  <File Type="PLACE-UTIL" Name="contBCD_VIO_utilization_placed.rpt"/>
  <File Type="PLACE-UTIL-PB" Name="contBCD_VIO_utilization_placed.pb"/>
  <File Type="PLACE-CTRL" Name="contBCD_VIO_control_sets_placed.rpt"/>
  <File Type="PLACE-SIMILARITY" Name="contBCD_VIO_incremental_reuse_placed.rpt"/>
  <File Type="PLACE-PRE-SIMILARITY" Name="contBCD_VIO_incremental_reuse_pre_placed.rpt"/>
  <File Type="PLACE-TIMING" Name="contBCD_VIO_timing_summary_placed.rpt"/>
  <File Type="POSTPLACE-PWROPT-DCP" Name="contBCD_VIO_postplace_pwropt.dcp"/>
  <File Type="POSTPLACE-PWROPT-TIMING" Name="contBCD_VIO_timing_summary_postplace_pwropted.rpt"/>
  <File Type="PHYSOPT-DCP" Name="contBCD_VIO_physopt.dcp"/>
  <File Type="PHYSOPT-DRC" Name="contBCD_VIO_drc_physopted.rpt"/>
  <File Type="BG-BIT" Name="contBCD_VIO.bit"/>
  <File Type="PHYSOPT-TIMING" Name="contBCD_VIO_timing_summary_physopted.rpt"/>
  <File Type="ROUTE-ERROR-DCP" Name="contBCD_VIO_routed_error.dcp"/>
  <File Type="ROUTE-DCP" Name="contBCD_VIO_routed.dcp"/>
  <File Type="ROUTE-BLACKBOX-DCP" Name="contBCD_VIO_routed_bb.dcp"/>
  <File Type="ROUTE-DRC" Name="contBCD_VIO_drc_routed.rpt"/>
  <File Type="ROUTE-DRC-PB" Name="contBCD_VIO_drc_routed.pb"/>
  <File Type="BITSTR-MSK" Name="contBCD_VIO.msk"/>
  <File Type="ROUTE-DRC-RPX" Name="contBCD_VIO_drc_routed.rpx"/>
  <File Type="BG-BGN" Name="contBCD_VIO.bgn"/>
  <File Type="ROUTE-METHODOLOGY-DRC" Name="contBCD_VIO_methodology_drc_routed.rpt"/>
  <File Type="BITSTR-RBT" Name="contBCD_VIO.rbt"/>
  <File Type="ROUTE-METHODOLOGY-DRC-RPX" Name="contBCD_VIO_methodology_drc_routed.rpx"/>
  <File Type="BG-BIN" Name="contBCD_VIO.bin"/>
  <File Type="ROUTE-METHODOLOGY-DRC-PB" Name="contBCD_VIO_methodology_drc_routed.pb"/>
  <File Type="ROUTE-PWR-RPX" Name="contBCD_VIO_power_routed.rpx"/>
  <File Type="ROUTE-STATUS" Name="contBCD_VIO_route_status.rpt"/>
  <File Type="ROUTE-STATUS-PB" Name="contBCD_VIO_route_status.pb"/>
  <File Type="ROUTE-TIMINGSUMMARY" Name="contBCD_VIO_timing_summary_routed.rpt"/>
  <File Type="ROUTE-TIMING-PB" Name="contBCD_VIO_timing_summary_routed.pb"/>
  <File Type="ROUTE-TIMING-RPX" Name="contBCD_VIO_timing_summary_routed.rpx"/>
  <File Type="ROUTE-SIMILARITY" Name="contBCD_VIO_incremental_reuse_routed.rpt"/>
  <File Type="RDI-RDI" Name="contBCD_VIO.vdi"/>
  <File Type="ROUTE-CLK" Name="contBCD_VIO_clock_utilization_routed.rpt"/>
  <File Type="POSTROUTE-PHYSOPT-DCP" Name="contBCD_VIO_postroute_physopt.dcp"/>
  <File Type="POSTROUTE-PHYSOPT-BLACKBOX-DCP" Name="contBCD_VIO_postroute_physopt_bb.dcp"/>
  <File Type="POSTROUTE-PHYSOPT-TIMING" Name="contBCD_VIO_timing_summary_postroute_physopted.rpt"/>
  <File Type="POSTROUTE-PHYSOPT-TIMING-PB" Name="contBCD_VIO_timing_summary_postroute_physopted.pb"/>
  <File Type="POSTROUTE-PHYSOPT-TIMING-RPX" Name="contBCD_VIO_timing_summary_postroute_physopted.rpx"/>
  <File Type="BITSTR-NKY" Name="contBCD_VIO.nky"/>
  <File Type="BITSTR-BMM" Name="contBCD_VIO_bd.bmm"/>
  <File Type="BITSTR-MMI" Name="contBCD_VIO.mmi"/>
  <File Type="BITSTR-LTX" Name="debug_nets.ltx"/>
  <File Type="BITSTR-LTX" Name="contBCD_VIO.ltx"/>
  <File Type="BITSTR-SYSDEF" Name="contBCD_VIO.sysdef"/>
  <File Type="WBT-USG" Name="usage_statistics_webtalk.html"/>
  <FileSet Name="sources" Type="DesignSrcs" RelSrcDir="$PSRCDIR/sources_1">
    <Filter Type="Srcs"/>
    <File Path="$PSRCDIR/sources_1/ip/vio_0/vio_0.xci">
      <FileInfo>
        <Attr Name="UsedIn" Val="synthesis"/>
        <Attr Name="UsedIn" Val="implementation"/>
        <Attr Name="UsedIn" Val="simulation"/>
      </FileInfo>
    </File>
    <File Path="$PPRDIR/../../15-cont-bcd-beh/Fuentes/contBCDBeh.vhd">
      <FileInfo>
        <Attr Name="UsedIn" Val="synthesis"/>
        <Attr Name="UsedIn" Val="simulation"/>
      </FileInfo>
    </File>
    <File Path="$PPRDIR/../Fuentes/contBCD_Lento.vhd">
      <FileInfo>
        <Attr Name="UsedIn" Val="synthesis"/>
        <Attr Name="UsedIn" Val="simulation"/>
      </FileInfo>
    </File>
    <File Path="$PPRDIR/../../17-gen-enable/Fuentes/genEna.vhd">
      <FileInfo>
        <Attr Name="UsedIn" Val="synthesis"/>
        <Attr Name="UsedIn" Val="simulation"/>
      </FileInfo>
    </File>
    <File Path="$PSRCDIR/sources_1/new/contBCD_VIO.vhd">
      <FileInfo>
        <Attr Name="UsedIn" Val="synthesis"/>
        <Attr Name="UsedIn" Val="simulation"/>
      </FileInfo>
    </File>
    <Config>
      <Option Name="DesignMode" Val="RTL"/>
      <Option Name="TopModule" Val="contBCD_VIO"/>
      <Option Name="TopAutoSet" Val="TRUE"/>
    </Config>
  </FileSet>
  <FileSet Name="constrs_in" Type="Constrs" RelSrcDir="$PSRCDIR/constrs_1">
    <Filter Type="Constrs"/>
    <File Path="$PPRDIR/../Fuentes/Arty-Z7-10-Master.xdc">
      <FileInfo>
        <Attr Name="UsedIn" Val="synthesis"/>
        <Attr Name="UsedIn" Val="implementation"/>
      </FileInfo>
    </File>
    <Config>
      <Option Name="ConstrsType" Val="XDC"/>
    </Config>
  </FileSet>
  <Strategy Version="1" Minor="2">
    <StratHandle Name="Vivado Implementation Defaults" Flow="Vivado Implementation 2018"/>
    <Step Id="init_design"/>
    <Step Id="opt_design"/>
    <Step Id="power_opt_design"/>
    <Step Id="place_design"/>
    <Step Id="post_place_power_opt_design"/>
    <Step Id="phys_opt_design"/>
    <Step Id="route_design"/>
    <Step Id="post_route_phys_opt_design"/>
    <Step Id="write_bitstream"/>
  </Strategy>
</GenRun>
